MANIFEST.in
README.txt
setup.py
cartouche/__init__.py
cartouche/_portability.py
cartouche/errors.py
cartouche/nodes.py
cartouche/parser.py
cartouche/sphinxext.py
cartouche/version.py
cartouche.egg-info/PKG-INFO
cartouche.egg-info/SOURCES.txt
cartouche.egg-info/dependency_links.txt
cartouche.egg-info/not-zip-safe
cartouche.egg-info/requires.txt
cartouche.egg-info/top_level.txt
cartouche/test/__init__.py
cartouche/test/test_comments.py
cartouche/test/test_issues.py
cartouche/test/test_nodes.py
cartouche/test/test_parser.py
docs/build/html/api.html
docs/build/html/changes.html
docs/build/html/faq.html
docs/build/html/genindex.html
docs/build/html/index.html
docs/build/html/installation.html
docs/build/html/search.html
docs/build/html/usage.html
docs/build/html/_images/select_html.png
docs/build/html/_static/basic.css
docs/build/html/_static/cartouche_217x152.png
docs/build/html/_static/cartouche_76x53.png
docs/build/html/_static/cartouche__trans_217x152.png
docs/build/html/_static/comment-bright.png
docs/build/html/_static/comment-close.png
docs/build/html/_static/comment.png
docs/build/html/_static/down-pressed.png
docs/build/html/_static/down.png
docs/build/html/_static/file.png
docs/build/html/_static/minus.png
docs/build/html/_static/nature.css
docs/build/html/_static/plus.png
docs/build/html/_static/pygments.css
docs/build/html/_static/select_html.png
docs/build/html/_static/up-pressed.png
docs/build/html/_static/up.png
docs/source/_static/cartouche_217x152.png
docs/source/_static/cartouche_76x53.png
docs/source/_static/cartouche__trans_217x152.png
docs/source/_static/select_html.png