Metadata-Version: 1.1
Name: cartouche
Version: 1.1.2
Summary: Sphinx "cartouche" extension
Home-page: https://github.com/rob-smallshire/cartouche
Author: Robert Smallshire
Author-email: robert@smallshire.org.uk
License: BSD
Download-URL: https://pypi.python.org/pypi/cartouche
Platform: any
Classifier: Development Status :: 5 - Production/Stable
Classifier: Environment :: Console
Classifier: Environment :: Web Environment
Classifier: Intended Audience :: Developers
Classifier: License :: OSI Approved :: BSD License
Classifier: Operating System :: OS Independent
Classifier: Programming Language :: Python
Classifier: Programming Language :: Python :: 2.7
Classifier: Programming Language :: Python :: 3
Classifier: Topic :: Documentation
Classifier: Topic :: Utilities
Requires: sphinx
